ghome_foyer_api/__init__.py
ghome_foyer_api/api.proto
ghome_foyer_api/api_pb2.py
ghome_foyer_api/api_pb2.pyi
ghome_foyer_api/api_pb2_grpc.py
ghome_foyer_api/api_pb2_grpc.pyi
ghome_foyer_api/py.typed
ghome_foyer_api-1.2.3.dist-info/METADATA
ghome_foyer_api-1.2.3.dist-info/WHEEL
ghome_foyer_api-1.2.3.dist-info/licenses/LICENSE
ghome_foyer_api-1.2.3.dist-info/RECORD
