Metadata-Version: 2.4
Name: ghome-foyer-api
Version: 1.2.3
Summary: Generated protobuf stubs for Google Home Foyer API
Project-URL: Homepage, https://github.com/KapJI/ghome-foyer-api
Project-URL: Bug Tracker, https://github.com/KapJI/ghome-foyer-api/issues
Project-URL: Release Notes, https://github.com/KapJI/ghome-foyer-api/releases
Author-email: Ruslan Sayfutdinov <ruslan@sayfutdinov.com>
License: MIT
License-File: LICENSE
Keywords: Foyer API,Google Home
Classifier: Development Status :: 3 - Alpha
Classifier: Intended Audience :: Developers
Classifier: License :: OSI Approved :: MIT License
Classifier: Operating System :: OS Independent
Classifier: Programming Language :: Python :: 3.9
Classifier: Programming Language :: Python :: 3.10
Classifier: Topic :: Software Development
Classifier: Typing :: Typed
Requires-Python: >=3.9
Requires-Dist: grpcio<2,>=1.71.0
Requires-Dist: protobuf>=6.31.0
